contextify/__init__.py
contextify/cli.py
contextify_cli-0.1.1.dist-info/licenses/LICENSE
contextify_cli-0.1.1.dist-info/METADATA
contextify_cli-0.1.1.dist-info/WHEEL
contextify_cli-0.1.1.dist-info/entry_points.txt
contextify_cli-0.1.1.dist-info/top_level.txt
contextify_cli-0.1.1.dist-info/RECORD
