Metadata-Version: 2.4
Name: contextify-cli
Version: 0.1.1
Summary: A CLI tool to prepare code as context for AI assistants and other purposes.
Author-email: Alessandro de Lima Calixto Alves <alessandrolcal@yahoo.com>
License:                                  Apache License
Project-URL: Homepage, https://github.com/alessandrolca/contextify
Keywords: ai,ai-assistant,cli,code,code-context,code-preparation,command-line,context,context-builder,developer-tool,development,llm,markdown,prompt-engineering,software-development,source-code,text-processing,utilities
Classifier: Development Status :: 3 - Alpha
Classifier: Intended Audience :: Developers
Classifier: Topic :: Text Processing :: Markup :: Markdown
Classifier: License :: OSI Approved :: Apache Software License
Classifier: Programming Language :: Python :: 3
Classifier: Programming Language :: Python :: 3.9
Classifier: Programming Language :: Python :: 3.10
Classifier: Programming Language :: Python :: 3.11
Classifier: Programming Language :: Python :: 3.12
Classifier: Operating System :: OS Independent
Classifier: Environment :: Console
Classifier: Topic :: Utilities
Requires-Python: >=3.9
License-File: LICENSE
Dynamic: license-file
